{"estimate":false,"updated_at":"16\/04 à 14h12","sources":["Ministère de l'Intérieur"],"slug":"\/elections\/seine-maritime_76","population":1275483,"registered":837659,"participation":{"percent":73.54000000000001,"number":616056},"abstained":{"percent":26.46,"number":221603},"real":{"percent":96.72,"number":595854},"blank":{"percent":3.28,"number":20202},"votes":{"Bruno Mégret":{"number":15861,"percent":2.66},"Corinne Lepage":{"number":10297,"percent":1.73},"Daniel Gluckstein":{"number":3316,"percent":0.5600000000000001},"François Bayrou":{"number":35963,"percent":6.04},"Jacques Chirac":{"number":113654,"percent":19.07},"Jean-Marie Le Pen":{"number":96671,"percent":16.22},"Christiane Taubira":{"number":11256,"percent":1.89},"Jean Saint-Josse":{"number":22320,"percent":3.75},"Noël Mamère":{"number":29290,"percent":4.92},"Lionel Jospin":{"number":100010,"percent":16.78},"Christine Boutin":{"number":5478,"percent":0.92},"Robert Hue":{"number":27170,"percent":4.56},"Jean-Pierre Chevènement":{"number":27872,"percent":4.68},"Alain Madelin":{"number":19315,"percent":3.24},"Arlette Laguiller":{"number":46966,"percent":7.88},"Olivier Besancenot":{"number":30415,"percent":5.1}}}